[
  {
    "id": "alien-covenant-2017-87gzhd-622618",
    "name": "Alien: Covenant (2017)",
    "url": "http://govfederal.org:80/movie/t1214c/87gzhd/622618.mp4",
    "logo": "https://image.tmdb.org/t/p/w780/wm8L1D3YMT0auLQiPXY3H1CUDg8.jpg",
    "category": "🎬 Coleção ALIEN",
    "type": "movie",
    "isAdult": false
  },
  {
    "id": "alien-o-oitavo-passageiro-1979-87gzhd-623402",
    "name": "Alien: O Oitavo Passageiro (1979)",
    "url": "http://govfederal.org:80/movie/t1214c/87gzhd/623402.mp4",
    "logo": "https://image.tmdb.org/t/p/w780/rFHzJrkO1kNIezb6rFog5oCJUEn.jpg",
    "category": "🎬 Coleção ALIEN",
    "type": "movie",
    "isAdult": false
  },
  {
    "id": "aliens-o-resgate-1986-87gzhd-1112281",
    "name": "Aliens: O Resgate (1986)",
    "url": "http://govfederal.org:80/movie/t1214c/87gzhd/1112281.mp4",
    "logo": "https://image.tmdb.org/t/p/w780/cORjIMhNxSukd09E6MlvwU5Ev1V.jpg",
    "category": "🎬 Coleção ALIEN",
    "type": "movie",
    "isAdult": false
  }
]